diambra/__init__.py
diambra/arena/__init__.py
diambra/arena/arena_gym.py
diambra/arena/env_settings.py
diambra/arena/make_env.py
diambra/arena/engine/__init__.py
diambra/arena/engine/interface.py
diambra/arena/ray_rllib/__init__.py
diambra/arena/ray_rllib/make_ray_env.py
diambra/arena/sheeprl/__init__.py
diambra/arena/sheeprl/make_sheeprl_env.py
diambra/arena/stable_baselines/__init__.py
diambra/arena/stable_baselines/make_sb_env.py
diambra/arena/stable_baselines/sb_utils.py
diambra/arena/stable_baselines3/__init__.py
diambra/arena/stable_baselines3/make_sb3_env.py
diambra/arena/stable_baselines3/sb3_utils.py
diambra/arena/utils/.splash_screen.gif
diambra/arena/utils/__init__.py
diambra/arena/utils/controller.py
diambra/arena/utils/diambra_data_loader.py
diambra/arena/utils/engine_mock.py
diambra/arena/utils/gym_utils.py
diambra/arena/utils/integratedGames.json
diambra/arena/utils/splash_screen.py
diambra/arena/wrappers/__init__.py
diambra/arena/wrappers/arena_wrappers.py
diambra/arena/wrappers/episode_recording.py
diambra/arena/wrappers/observation.py
diambra_arena-2.2.7.dist-info/LICENSE.txt
diambra_arena-2.2.7.dist-info/METADATA
diambra_arena-2.2.7.dist-info/WHEEL
diambra_arena-2.2.7.dist-info/top_level.txt
diambra_arena-2.2.7.dist-info/RECORD
