Metadata-Version: 2.1
Name: diambra-arena
Version: 2.2.7
Summary: DIAMBRA™ Arena. Built with OpenAI Gym Python interface, easy to use, transforms popular video games into Reinforcement Learning environments
Home-page: https://github.com/diambra/arena
Author: DIAMBRA Team
Author-email: info@diambra.ai
License: Custom
Classifier: Development Status :: 3 - Alpha
Classifier: Operating System :: OS Independent
Classifier: Programming Language :: Python
Classifier: Programming Language :: Python :: 3
Classifier: Topic :: Scientific/Engineering :: Artificial Intelligence
Classifier: Topic :: Scientific/Engineering :: Artificial Life
Classifier: Topic :: Games/Entertainment
Classifier: Topic :: Games/Entertainment :: Arcade
Classifier: Topic :: Education
License-File: LICENSE.txt
Requires-Dist: gymnasium >=0.26.3
Requires-Dist: inputs
Requires-Dist: screeninfo
Requires-Dist: tk
Requires-Dist: opencv-python >=4.4.0.42
Requires-Dist: grpcio
Requires-Dist: diambra-engine >=2.2.3
Requires-Dist: dacite
Requires-Dist: importlib-metadata <=4.12.0 ; python_version <= "3.7"
Provides-Extra: core
Provides-Extra: ray-rllib
Requires-Dist: ray[rllib] ~=2.7.0 ; extra == 'ray-rllib'
Requires-Dist: torch ; extra == 'ray-rllib'
Requires-Dist: pyyaml ; extra == 'ray-rllib'
Provides-Extra: sheeprl
Requires-Dist: sheeprl ==0.5.5 ; extra == 'sheeprl'
Requires-Dist: importlib-resources ==6.1.0 ; extra == 'sheeprl'
Provides-Extra: stable-baselines
Requires-Dist: stable-baselines ~=2.10.2 ; extra == 'stable-baselines'
Requires-Dist: gym <=0.21.0 ; extra == 'stable-baselines'
Requires-Dist: protobuf ==3.20.1 ; extra == 'stable-baselines'
Requires-Dist: pyyaml ; extra == 'stable-baselines'
Provides-Extra: stable-baselines3
Requires-Dist: stable-baselines3[extra] ~=2.1.0 ; extra == 'stable-baselines3'
Requires-Dist: pyyaml ; extra == 'stable-baselines3'
Provides-Extra: tests
Requires-Dist: pytest ; extra == 'tests'
Requires-Dist: pytest-mock ; extra == 'tests'
Requires-Dist: testresources ; extra == 'tests'
